ssh_assist.py
ssh_assist-0.0.4.dist-info/licenses/LICENSE
ssh_assist-0.0.4.dist-info/METADATA
ssh_assist-0.0.4.dist-info/WHEEL
ssh_assist-0.0.4.dist-info/entry_points.txt
ssh_assist-0.0.4.dist-info/top_level.txt
ssh_assist-0.0.4.dist-info/RECORD
