Metadata-Version: 2.4
Name: ssh-assist
Version: 0.0.4
Summary: Some ssh features the way I want it
Author-email: Adwaith-Rajesh <me@adwaith.dev>
License-Expression: MIT
Project-URL: Homepage, https://github.com/Adwaith-Rajesh/ssh-assist
Classifier: Programming Language :: Python :: 3
Classifier: Operating System :: OS Independent
Requires-Python: >=3.12
License-File: LICENSE
Requires-Dist: argcomplete>=3.6.2
Dynamic: license-file
